demo/__init__.py
demo/local_settings.py
demo/sass_variables.py
demo/settings.py
demo/urls.py
demo/views.py
demo/wsgi.py
psu_authorize/__init__.py
psu_authorize/admin.py
psu_authorize/apps.py
psu_authorize/models.py
psu_authorize/urls.py
psu_authorize/views.py
psu_authorize/classes/Application.py
psu_authorize/classes/Authority.py
psu_authorize/classes/Permission.py
psu_authorize/classes/__init__.py
psu_authorize/migrations/__init__.py
psu_authorize/services/__init__.py
psu_authorize/services/authorization_service.py
psu_authorize/templates/psu_authorize/index.html
psu_authorize/templates/psu_authorize/applications/_rows.html
psu_authorize/templates/psu_authorize/applications/index.html
psu_authorize/templates/psu_authorize/applications/index.js
psu_authorize/templates/psu_authorize/authorities/_rows.html
psu_authorize/templates/psu_authorize/authorities/index.html
psu_authorize/templates/psu_authorize/authorities/index.js
psu_authorize/templates/psu_authorize/permissions/_app_permission.html
psu_authorize/templates/psu_authorize/permissions/_app_permission_rows.html
psu_authorize/templates/psu_authorize/permissions/authorize_app.html
psu_authorize/templates/psu_authorize/permissions/permissions.js
psu_authorize/templatetags/__init__.py
psu_authorize/templatetags/authorize_taglib.py
psu_authorize/tests/__init__.py
psu_authorize/tests/test_applications.py
psu_authorize-2.0.0.dist-info/METADATA
psu_authorize-2.0.0.dist-info/WHEEL
psu_authorize-2.0.0.dist-info/top_level.txt
psu_authorize-2.0.0.dist-info/RECORD
